<annotation>
	<folder>00_arash</folder>
	<filename>image_0329.jpg</filename>
	<path>/home/amrl/Desktop/00_arash/image_0329.jpg</path>
	<source>
		<database>Unknown</database>
	</source>
	<size>
		<width>520</width>
		<height>252</height>
		<depth>3</depth>
	</size>
	<segmented>0</segmented>
	<object>
		<name>flammable-solid</name>
		<pose>Unspecified</pose>
		<truncated>0</truncated>
		<difficult>0</difficult>
		<bndbox>
			<xmin>87</xmin>
			<ymin>109</ymin>
			<xmax>128</xmax>
			<ymax>152</ymax>
		</bndbox>
	</object>
	<object>
		<name>flammable-solid</name>
		<pose>Unspecified</pose>
		<truncated>0</truncated>
		<difficult>0</difficult>
		<bndbox>
			<xmin>226</xmin>
			<ymin>119</ymin>
			<xmax>272</xmax>
			<ymax>164</ymax>
		</bndbox>
	</object>
	<object>
		<name>flammable-solid</name>
		<pose>Unspecified</pose>
		<truncated>0</truncated>
		<difficult>0</difficult>
		<bndbox>
			<xmin>376</xmin>
			<ymin>121</ymin>
			<xmax>443</xmax>
			<ymax>185</ymax>
		</bndbox>
	</object>
</annotation>