<annotation>
	<folder>00_misaq</folder>
	<filename>image_1528.jpg</filename>
	<path>/home/misaq/00_misaq/image_1528.jpg</path>
	<source>
		<database>Unknown</database>
	</source>
	<size>
		<width>520</width>
		<height>252</height>
		<depth>3</depth>
	</size>
	<segmented>0</segmented>
	<object>
		<name>flammable-solid</name>
		<pose>Unspecified</pose>
		<truncated>0</truncated>
		<difficult>0</difficult>
		<bndbox>
			<xmin>200</xmin>
			<ymin>103</ymin>
			<xmax>331</xmax>
			<ymax>223</ymax>
		</bndbox>
	</object>
	<object>
		<name>flammable-solid</name>
		<pose>Unspecified</pose>
		<truncated>1</truncated>
		<difficult>0</difficult>
		<bndbox>
			<xmin>78</xmin>
			<ymin>1</ymin>
			<xmax>128</xmax>
			<ymax>39</ymax>
		</bndbox>
	</object>
	<object>
		<name>flammable-solid</name>
		<pose>Unspecified</pose>
		<truncated>1</truncated>
		<difficult>0</difficult>
		<bndbox>
			<xmin>1</xmin>
			<ymin>121</ymin>
			<xmax>55</xmax>
			<ymax>172</ymax>
		</bndbox>
	</object>
</annotation>