<annotation>
	<folder>00_arshia</folder>
	<filename>image_1293.jpg</filename>
	<path>/home/amrl/Desktop/00_arshia/image_1293.jpg</path>
	<source>
		<database>Unknown</database>
	</source>
	<size>
		<width>520</width>
		<height>520</height>
		<depth>3</depth>
	</size>
	<segmented>0</segmented>
	<object>
		<name>oxygen</name>
		<pose>Unspecified</pose>
		<truncated>0</truncated>
		<difficult>0</difficult>
		<bndbox>
			<xmin>152</xmin>
			<ymin>124</ymin>
			<xmax>189</xmax>
			<ymax>158</ymax>
		</bndbox>
	</object>
	<object>
		<name>oxygen</name>
		<pose>Unspecified</pose>
		<truncated>0</truncated>
		<difficult>0</difficult>
		<bndbox>
			<xmin>362</xmin>
			<ymin>176</ymin>
			<xmax>422</xmax>
			<ymax>240</ymax>
		</bndbox>
	</object>
	<object>
		<name>oxygen</name>
		<pose>Unspecified</pose>
		<truncated>0</truncated>
		<difficult>0</difficult>
		<bndbox>
			<xmin>246</xmin>
			<ymin>321</ymin>
			<xmax>293</xmax>
			<ymax>366</ymax>
		</bndbox>
	</object>
	<object>
		<name>oxygen</name>
		<pose>Unspecified</pose>
		<truncated>0</truncated>
		<difficult>0</difficult>
		<bndbox>
			<xmin>95</xmin>
			<ymin>272</ymin>
			<xmax>143</xmax>
			<ymax>317</ymax>
		</bndbox>
	</object>
</annotation>