<annotation>
	<folder>00_arash</folder>
	<filename>image_0170.jpg</filename>
	<path>/home/amrl/Desktop/00_arash/image_0170.jpg</path>
	<source>
		<database>Unknown</database>
	</source>
	<size>
		<width>520</width>
		<height>520</height>
		<depth>3</depth>
	</size>
	<segmented>0</segmented>
	<object>
		<name>oxygen</name>
		<pose>Unspecified</pose>
		<truncated>0</truncated>
		<difficult>0</difficult>
		<bndbox>
			<xmin>182</xmin>
			<ymin>250</ymin>
			<xmax>286</xmax>
			<ymax>344</ymax>
		</bndbox>
	</object>
	<object>
		<name>oxygen</name>
		<pose>Unspecified</pose>
		<truncated>1</truncated>
		<difficult>0</difficult>
		<bndbox>
			<xmin>477</xmin>
			<ymin>72</ymin>
			<xmax>520</xmax>
			<ymax>108</ymax>
		</bndbox>
	</object>
</annotation>